anolis
setup.py
anolis.egg-info/PKG-INFO
anolis.egg-info/SOURCES.txt
anolis.egg-info/dependency_links.txt
anolis.egg-info/requires.txt
anolis.egg-info/top_level.txt
anolislib/__init__.py
anolislib/generator.py
anolislib/utils.py
anolislib/processes/__init__.py
anolislib/processes/annotate.py
anolislib/processes/filter.py
anolislib/processes/lof.py
anolislib/processes/outliner.py
anolislib/processes/refs.py
anolislib/processes/replaceHeadings.py
anolislib/processes/sub.py
anolislib/processes/terms.py
anolislib/processes/toc.py
anolislib/processes/xref.py
anolislib/processes/xspecxref.py