Metadata-Version: 1.0
Name: anolis
Version: 1.2
Summary: HTML document post-processor
Home-page: https://bitbucket.org/ms2ger/anolis/
Author: Ms2ger
Author-email: Ms2ger@gmail.com
License: MIT
Download-URL: https://bitbucket.org/ms2ger/anolis/downloads
Platform: UNKNOWN
Classifier: Development Status :: 5 - Production/Stable
Classifier: Environment :: Console
Classifier: Intended Audience :: Developers
Classifier: License :: OSI Approved :: MIT License
Classifier: Operating System :: OS Independent
Classifier: Programming Language :: Python :: 2
Classifier: Topic :: Text Processing :: Markup :: HTML
